{"playerFirstName": "Mathias", "playerLastName": "Melton", "playerFullName": "Mathias Melton", "playerHeight": "6'0''", "playerWeight": 170, "playerImage": "null", "playerCountryImage": "null", "playerHandedness": "Right", "playerPersonality": "Going", "attributes": {"physical": {"agility": 9, "flexibility": 7, "balance": 10, "stamina": 8, "strength": 9}, "playerCondition": 50, "mental": {"awareness": 8, "determination": 10, "positivity": 7, "demeanor": 9, "fortitude": 7}, "equipment": {"fit": 6, "quality": 20, "accuracy": 18}, "mechanics": {"ballStriking": 7, "accuracy": 10, "swing": 10, "tempo": 10, "shotShaping": 7}}}