{"playerFirstName": "Jiraiya", "playerLastName": "Paul", "playerFullName": "Jiraiya Paul", "playerHeight": "5'6''", "playerWeight": 183, "playerImage": "null", "playerCountryImage": "null", "playerHandedness": "Right", "playerPersonality": "Easy", "attributes": {"physical": {"agility": 8, "flexibility": 5, "balance": 8, "stamina": 5, "strength": 5}, "playerCondition": 50, "mental": {"awareness": 10, "determination": 5, "positivity": 10, "demeanor": 7, "fortitude": 5}, "equipment": {"fit": 10, "quality": 15, "accuracy": 18}, "mechanics": {"ballStriking": 7, "accuracy": 4, "swing": 8, "tempo": 9, "shotShaping": 8}}}