{"playerFirstName": "Colson", "playerLastName": "Stanton", "playerFullName": "Colson Stanton", "playerHeight": "6'2''", "playerWeight": 162, "playerImage": "null", "playerCountryImage": "null", "playerHandedness": "Right", "playerPersonality": "Professional", "attributes": {"physical": {"agility": 8, "flexibility": 8, "balance": 10, "stamina": 4, "strength": 4}, "playerCondition": 50, "mental": {"awareness": 9, "determination": 10, "positivity": 8, "demeanor": 4, "fortitude": 10}, "equipment": {"fit": 5, "quality": 8, "accuracy": 16}, "mechanics": {"ballStriking": 10, "accuracy": 6, "swing": 4, "tempo": 10, "shotShaping": 7}}}