{"playerFirstName": "Makai", "playerLastName": "Chung", "playerFullName": "Makai Chung", "playerHeight": "5'7''", "playerWeight": 232, "playerImage": "null", "playerCountryImage": "null", "playerHandedness": "Right", "playerPersonality": "Going", "attributes": {"physical": {"agility": 3, "flexibility": 2, "balance": 3, "stamina": 1, "strength": 1}, "playerCondition": 50, "mental": {"awareness": 3, "determination": 3, "positivity": 5, "demeanor": 2, "fortitude": 6}, "equipment": {"fit": 5, "quality": 11, "accuracy": 4}, "mechanics": {"ballStriking": 2, "accuracy": 3, "swing": 3, "tempo": 4, "shotShaping": 6}}}