{"playerFirstName": "Clayton", "playerLastName": "Sawyer", "playerFullName": "Clayton Sawyer", "playerHeight": "6'1''", "playerWeight": 180, "playerImage": "null", "playerCountryImage": "null", "playerHandedness": "Right", "playerPersonality": "Professional", "attributes": {"physical": {"agility": 10, "flexibility": 10, "balance": 7, "stamina": 7, "strength": 10}, "playerCondition": 50, "mental": {"awareness": 4, "determination": 4, "positivity": 6, "demeanor": 9, "fortitude": 4}, "equipment": {"fit": 3, "quality": 12, "accuracy": 20}, "mechanics": {"ballStriking": 8, "accuracy": 1, "swing": 8, "tempo": 7, "shotShaping": 10}}}