{"playerFirstName": "Jaxx", "playerLastName": "Roman", "playerFullName": "Jaxx Roman", "playerHeight": "6'0''", "playerWeight": 285, "playerImage": "null", "playerCountryImage": "null", "playerHandedness": "Right", "playerPersonality": "Stubborn", "attributes": {"physical": {"agility": 4, "flexibility": 9, "balance": 10, "stamina": 2, "strength": 3}, "playerCondition": 50, "mental": {"awareness": 4, "determination": 7, "positivity": 9, "demeanor": 5, "fortitude": 2}, "equipment": {"fit": 3, "quality": 6, "accuracy": 17}, "mechanics": {"ballStriking": 1, "accuracy": 6, "swing": 1, "tempo": 10, "shotShaping": 9}}}