{"playerFirstName": "Castiel", "playerLastName": "Shah", "playerFullName": "Castiel Shah", "playerHeight": "5'5''", "playerWeight": 164, "playerImage": "null", "playerCountryImage": "null", "playerHandedness": "Right", "playerPersonality": "Friendly", "attributes": {"physical": {"agility": 10, "flexibility": 4, "balance": 10, "stamina": 8, "strength": 2}, "playerCondition": 50, "mental": {"awareness": 7, "determination": 5, "positivity": 9, "demeanor": 8, "fortitude": 8}, "equipment": {"fit": 7, "quality": 17, "accuracy": 10}, "mechanics": {"ballStriking": 7, "accuracy": 7, "swing": 2, "tempo": 7, "shotShaping": 2}}}