{"playerFirstName": "Emir", "playerLastName": "Chase", "playerFullName": "Emir Chase", "playerHeight": "6'2''", "playerWeight": 204, "playerImage": "null", "playerCountryImage": "null", "playerHandedness": "Right", "playerPersonality": "Professional", "attributes": {"physical": {"agility": 8, "flexibility": 7, "balance": 9, "stamina": 9, "strength": 10}, "playerCondition": 50, "mental": {"awareness": 2, "determination": 4, "positivity": 6, "demeanor": 4, "fortitude": 7}, "equipment": {"fit": 3, "quality": 9, "accuracy": 14}, "mechanics": {"ballStriking": 6, "accuracy": 7, "swing": 2, "tempo": 6, "shotShaping": 7}}}